<configuration>
  <property>
    <name>mapreduce.framework.name</name>
    <value>yarn</value>
  </property>
  <property>
    <name>mapreduce.map.memory.mb</name>
    <value>3072</value>
  </property>
  <property>
    <name>mapreduce.reduce.memory.mb</name>
    <value>3072</value>
  </property>
  <property>
    <name>mapreduce.map.java.opts</name>
    <value>-Xmx3G</value>
  </property>
  <property>
    <name>mapreduce.reduce.java.opts</name>
    <value>-Xmx3G</value>
  </property>
  <property>
    <name>mapred.child.java.opts</name>
    <value>-Xmx3G -XX:+UseConcMarkSweepGC</value>
  </property>
  <property>
    <name>yarn.app.mapreduce.am.env</name>
    <value>HADOOP_MAPRED_HOME=/usr/local/hadoop</value>
  </property>
  <property>
    <name>mapreduce.map.env</name>
    <value>HADOOP_MAPRED_HOME=/usr/local/hadoop</value>
  </property>
  <property>
    <name>mapreduce.reduce.env</name>
    <value>HADOOP_MAPRED_HOME=/usr/local/hadoop</value>
  </property>
</configuration>
